scikit_multilearn-0.1.0.dist-info/DESCRIPTION.rst
scikit_multilearn-0.1.0.dist-info/METADATA
scikit_multilearn-0.1.0.dist-info/RECORD
scikit_multilearn-0.1.0.dist-info/WHEEL
scikit_multilearn-0.1.0.dist-info/metadata.json
scikit_multilearn-0.1.0.dist-info/top_level.txt
skmultilearn/__init__.py
skmultilearn/dataset.py
skmultilearn/utils.py
skmultilearn/adapt/__init__.py
skmultilearn/adapt/brknn.py
skmultilearn/adapt/mlaram.py
skmultilearn/adapt/mlknn.py
skmultilearn/base/__init__.py
skmultilearn/base/base.py
skmultilearn/base/mock.py
skmultilearn/base/problem_transformation.py
skmultilearn/cluster/__init__.py
skmultilearn/cluster/base.py
skmultilearn/cluster/fixed.py
skmultilearn/cluster/graphtool.py
skmultilearn/cluster/helpers.py
skmultilearn/cluster/igraph.py
skmultilearn/cluster/matrix.py
skmultilearn/cluster/networkx.py
skmultilearn/cluster/random.py
skmultilearn/ensemble/__init__.py
skmultilearn/ensemble/partition.py
skmultilearn/ensemble/rakeld.py
skmultilearn/ensemble/rakelo.py
skmultilearn/ensemble/voting.py
skmultilearn/ext/__init__.py
skmultilearn/ext/meka.py
skmultilearn/model_selection/__init__.py
skmultilearn/model_selection/iterative_stratification.py
skmultilearn/model_selection/measures.py
skmultilearn/problem_transform/__init__.py
skmultilearn/problem_transform/br.py
skmultilearn/problem_transform/cc.py
skmultilearn/problem_transform/lp.py
